pyblake2.cp36-win32.pyd
pyblake2-1.1.1.dist-info/DESCRIPTION.rst
pyblake2-1.1.1.dist-info/METADATA
pyblake2-1.1.1.dist-info/RECORD
pyblake2-1.1.1.dist-info/WHEEL
pyblake2-1.1.1.dist-info/metadata.json
pyblake2-1.1.1.dist-info/top_level.txt
