Metadata-Version: 2.0
Name: pyblake2
Version: 1.1.1
Summary: BLAKE2 hash function extension module
Home-page: https://github.com/dchest/pyblake2
Author: Dmitry Chestnykh
Author-email: dmitry@codingrobots.com
License: http://creativecommons.org/publicdomain/zero/1.0/
Platform: UNKNOWN
Classifier: Intended Audience :: Developers
Classifier: Intended Audience :: Information Technology
Classifier: Intended Audience :: Science/Research
Classifier: License :: CC0 1.0 Universal (CC0 1.0) Public Domain Dedication
Classifier: Operating System :: OS Independent
Classifier: Programming Language :: Python :: 2
Classifier: Programming Language :: Python :: 2.6
Classifier: Programming Language :: Python :: 2.7
Classifier: Programming Language :: Python :: 3
Classifier: Programming Language :: Python :: 3.0
Classifier: Programming Language :: Python :: 3.1
Classifier: Programming Language :: Python :: 3.2
Classifier: Programming Language :: Python :: 3.3
Classifier: Topic :: Security :: Cryptography
